[
  {
    "provincia": "Buenos Aires",
    "temperatura": 26.4,
    "humedad": 55.0,
    "precipitacion": null,
    "viento": 5.4,
    "coco": null,
    "icono": "unknown.svg",
    "condicion": "Desconocido",
    "fecha_hora": "2025-11-03 15:00:00 -03"
  },
  {
    "provincia": "Catamarca",
    "temperatura": 33.5,
    "humedad": 27.0,
    "precipitacion": 0.0,
    "viento": 38.9,
    "coco": 2,
    "icono": "fair.svg",
    "condicion": "Parcialmente despejado",
    "fecha_hora": "2025-11-03 15:00:00 -03"
  },
  {
    "provincia": "Chaco",
    "temperatura": 29.7,
    "humedad": 47.0,
    "precipitacion": null,
    "viento": 6.8,
    "coco": null,
    "icono": "unknown.svg",
    "condicion": "Desconocido",
    "fecha_hora": "2025-11-03 15:00:00 -03"
  },
  {
    "provincia": "Chubut",
    "temperatura": 16.9,
    "humedad": 27.0,
    "precipitacion": null,
    "viento": 24.1,
    "coco": null,
    "icono": "unknown.svg",
    "condicion": "Desconocido",
    "fecha_hora": "2025-11-03 15:00:00 -03"
  },
  {
    "provincia": "Corrientes",
    "temperatura": 29.7,
    "humedad": 47.0,
    "precipitacion": null,
    "viento": 6.8,
    "coco": null,
    "icono": "unknown.svg",
    "condicion": "Desconocido",
    "fecha_hora": "2025-11-03 15:00:00 -03"
  },
  {
    "provincia": "Córdoba",
    "temperatura": 31.0,
    "humedad": 28.0,
    "precipitacion": null,
    "viento": 11.2,
    "coco": null,
    "icono": "unknown.svg",
    "condicion": "Desconocido",
    "fecha_hora": "2025-11-03 15:00:00 -03"
  },
  {
    "provincia": "Entre Ríos",
    "temperatura": 28.8,
    "humedad": 44.0,
    "precipitacion": null,
    "viento": 8.6,
    "coco": null,
    "icono": "unknown.svg",
    "condicion": "Desconocido",
    "fecha_hora": "2025-11-03 15:00:00 -03"
  },
  {
    "provincia": "Formosa",
    "temperatura": 30.3,
    "humedad": 52.0,
    "precipitacion": null,
    "viento": 1.4,
    "coco": null,
    "icono": "unknown.svg",
    "condicion": "Desconocido",
    "fecha_hora": "2025-11-03 15:00:00 -03"
  },
  {
    "provincia": "Jujuy",
    "temperatura": 30.1,
    "humedad": 38.0,
    "precipitacion": 0.0,
    "viento": 16.7,
    "coco": 2,
    "icono": "fair.svg",
    "condicion": "Parcialmente despejado",
    "fecha_hora": "2025-11-03 15:00:00 -03"
  },
  {
    "provincia": "La Pampa",
    "temperatura": 25.3,
    "humedad": 40.0,
    "precipitacion": 0.0,
    "viento": 18.5,
    "coco": 3,
    "icono": "cloudy.svg",
    "condicion": "Parcialmente nublado",
    "fecha_hora": "2025-11-03 15:00:00 -03"
  },
  {
    "provincia": "La Rioja",
    "temperatura": 33.8,
    "humedad": 22.0,
    "precipitacion": null,
    "viento": 6.8,
    "coco": null,
    "icono": "unknown.svg",
    "condicion": "Desconocido",
    "fecha_hora": "2025-11-03 15:00:00 -03"
  },
  {
    "provincia": "Mendoza",
    "temperatura": 29.0,
    "humedad": 20.0,
    "precipitacion": 0.0,
    "viento": 13.0,
    "coco": 2,
    "icono": "fair.svg",
    "condicion": "Parcialmente despejado",
    "fecha_hora": "2025-11-03 15:00:00 -03"
  },
  {
    "provincia": "Misiones",
    "temperatura": 29.1,
    "humedad": 51.0,
    "precipitacion": null,
    "viento": 8.6,
    "coco": null,
    "icono": "unknown.svg",
    "condicion": "Desconocido",
    "fecha_hora": "2025-11-03 15:00:00 -03"
  },
  {
    "provincia": "Neuquén",
    "temperatura": 23.7,
    "humedad": 17.0,
    "precipitacion": null,
    "viento": 11.9,
    "coco": null,
    "icono": "unknown.svg",
    "condicion": "Desconocido",
    "fecha_hora": "2025-11-03 15:00:00 -03"
  },
  {
    "provincia": "Río Negro",
    "temperatura": 14.7,
    "humedad": 52.0,
    "precipitacion": null,
    "viento": 28.1,
    "coco": null,
    "icono": "unknown.svg",
    "condicion": "Desconocido",
    "fecha_hora": "2025-11-03 15:00:00 -03"
  },
  {
    "provincia": "Salta",
    "temperatura": 27.7,
    "humedad": 38.0,
    "precipitacion": null,
    "viento": 13.7,
    "coco": null,
    "icono": "unknown.svg",
    "condicion": "Desconocido",
    "fecha_hora": "2025-11-03 15:00:00 -03"
  },
  {
    "provincia": "San Juan",
    "temperatura": 29.5,
    "humedad": 23.0,
    "precipitacion": null,
    "viento": 5.8,
    "coco": null,
    "icono": "unknown.svg",
    "condicion": "Desconocido",
    "fecha_hora": "2025-11-03 15:00:00 -03"
  },
  {
    "provincia": "San Luis",
    "temperatura": 28.5,
    "humedad": 33.0,
    "precipitacion": null,
    "viento": 7.6,
    "coco": null,
    "icono": "unknown.svg",
    "condicion": "Desconocido",
    "fecha_hora": "2025-11-03 15:00:00 -03"
  },
  {
    "provincia": "Santa Cruz",
    "temperatura": 10.1,
    "humedad": 36.0,
    "precipitacion": null,
    "viento": 49.7,
    "coco": null,
    "icono": "unknown.svg",
    "condicion": "Desconocido",
    "fecha_hora": "2025-11-03 15:00:00 -03"
  },
  {
    "provincia": "Santa Fe",
    "temperatura": 29.0,
    "humedad": 45.0,
    "precipitacion": null,
    "viento": 5.8,
    "coco": null,
    "icono": "unknown.svg",
    "condicion": "Desconocido",
    "fecha_hora": "2025-11-03 15:00:00 -03"
  },
  {
    "provincia": "Santiago del Estero",
    "temperatura": 33.3,
    "humedad": 31.0,
    "precipitacion": null,
    "viento": 18.4,
    "coco": null,
    "icono": "unknown.svg",
    "condicion": "Desconocido",
    "fecha_hora": "2025-11-03 15:00:00 -03"
  },
  {
    "provincia": "Tierra del Fuego",
    "temperatura": 3.5,
    "humedad": 79.0,
    "precipitacion": 0.2,
    "viento": 42.6,
    "coco": 12,
    "icono": "sleet.svg",
    "condicion": "Aguanieve (constante)",
    "fecha_hora": "2025-11-03 15:00:00 -03"
  },
  {
    "provincia": "Tucumán",
    "temperatura": 33.1,
    "humedad": 32.0,
    "precipitacion": null,
    "viento": 11.2,
    "coco": null,
    "icono": "unknown.svg",
    "condicion": "Desconocido",
    "fecha_hora": "2025-11-03 15:00:00 -03"
  }
]